<nodes>
    <!-- Temperature -->
    <node>
        <nodeId>105</nodeId>
        <childId>0</childId>
        <ack>0</ack>
        <msgType>1</msgType>
        <subType>0</subType>
        <msg_min>15</msg_min>
        <msg_max>45</msg_max>
        <sendDelay>10000</sendDelay>
    </node>
    <!-- Humidity -->
    <node>
        <nodeId>105</nodeId>
        <childId>1</childId>
        <ack>0</ack>
        <msgType>1</msgType>
        <subType>1</subType>
        <msg_min>40</msg_min>
        <msg_max>95</msg_max>
        <sendDelay>10000</sendDelay>
    </node>
    <!-- Light -->
    <node>
        <nodeId>106</nodeId>
        <childId>0</childId>
        <ack>0</ack>
        <msgType>1</msgType>
        <subType>2</subType>
        <sendDelay>10000</sendDelay>
        <answerAck>0</answerAck>
    </node>
    <!-- Light/Status Request -->
    <node>
        <nodeId>107</nodeId>
        <childId>0</childId>
        <ack>0</ack>
        <msgType>2</msgType>
        <subType>2</subType>
        <sendDelay>70000</sendDelay>
        <answerAck>0</answerAck>
    </node>
    <!--  V_VAR Request -->
    <node>
        <nodeId>1</nodeId>
        <childId>252</childId>
        <ack>0</ack>
        <msgType>2</msgType>
        <subType>24</subType>
        <sendDelay>7000</sendDelay>
        <answerAck>0</answerAck>
    </node>
</nodes>